dirtreegen/__init__.py
dirtreegen/dirtreegen.py
dirtreegen-0.0.3.dist-info/LICENSE
dirtreegen-0.0.3.dist-info/METADATA
dirtreegen-0.0.3.dist-info/WHEEL
dirtreegen-0.0.3.dist-info/entry_points.txt
dirtreegen-0.0.3.dist-info/top_level.txt
dirtreegen-0.0.3.dist-info/RECORD
