Metadata-Version: 2.1
Name: dirtreegen
Version: 0.0.3
Summary: Generate directory tree
Home-page: https://github.com/pythonqi/dirtreegen
Author: pythonqi
Author-email: pythonqi@outlook.com
License: MIT
Platform: UNKNOWN
Classifier: Programming Language :: Python :: 3
Classifier: License :: OSI Approved :: MIT License
Classifier: Operating System :: OS Independent
Requires-Dist: anytree (==2.4.3)
Requires-Dist: six (==1.11.0)
